relatorio/__init__.py
relatorio/reporting.py
relatorio/templates/__init__.py
relatorio/templates/base.py
relatorio/templates/chart.py
relatorio/templates/opendocument.py
relatorio/templates/pdf.py
relatorio/tests/__init__.py
relatorio/tests/egg.jpg
relatorio/tests/one.jpg
relatorio/tests/test.fodt
relatorio/tests/test.odt
relatorio/tests/test_api.py
relatorio/tests/test_odt.py
relatorio/tests/two.png
relatorio/tests/templates/include.tmpl
relatorio/tests/templates/other.tmpl
relatorio/tests/templates/test.tmpl
relatorio/tests/templates/time.tmpl
relatorio-0.11.0.data/scripts/relatorio-render
relatorio-0.11.0.dist-info/LICENSE
relatorio-0.11.0.dist-info/METADATA
relatorio-0.11.0.dist-info/WHEEL
relatorio-0.11.0.dist-info/top_level.txt
relatorio-0.11.0.dist-info/RECORD
